{
    "type": "equipment",
    "item_id": 2599,
    "name": "Silk Bliaut",
    "info": "",
    "icon": {
        "icon_id": 767,
        "color_id": 9
    },
    "jobs": [
        "Fighter",
        "Seeker",
        "Hunter",
        "Priest",
        "ShieldSage",
        "Sorcerer",
        "Warrior",
        "ElementArcher",
        "Alchemist",
        "SpiritLancer",
        "HighScepter"
    ],
    "sell_price": 1500,
    "weight": 5,
    "item_level": 9,
    "crest_slots": 0,
    "quality": 1,
    "can_bazaar": false,
    "color_id": 2,
    "equip_slot": "EQUIP_CATEGORY_WEAR_BODY",
    "level": 41,
    "genders": [
        "Male",
        "Female"
    ],
    "stats": {
        "attack": 0,
        "defense": 51,
        "magic_attack": 0,
        "magic_defense": 51,
        "crest_slot": 4,
        "ele_slot": 8
    },
    "params": [
        {
            "id": 68,
            "name": "MAX_HEALTH",
            "value": 276
        }
    ],
    "craft_recipe": [],
    "gradeup_recipe": [
        {
            "item_id": 7939,
            "amount": 1
        },
        {
            "item_id": 7987,
            "amount": 1
        }
    ],
    "previous_item_id": 987,
    "next_item_id": 3622
}