{
    "type": "material",
    "item_id": 16050,
    "name": "Crest of Herculean Power (Lowered Defense)",
    "info": "A crest that enhances the performance of the\nequipped weapon.",
    "icon": {
        "icon_id": 1047,
        "color_id": 106
    },
    "jobs": [],
    "sell_price": 100,
    "weight": 0,
    "item_level": 20,
    "crest_slots": 0,
    "quality": 0,
    "can_bazaar": false,
    "craft_recipe": [],
    "gradeup_recipe": [],
    "previous_item_id": 0,
    "next_item_id": 0,
    "shops": [],
    "gather": [],
    "hunt": []
}