{
    "type": "material",
    "item_id": 8019,
    "name": "Broken Dagger",
    "info": "Miscellaneous Crafting Material:\nA dagger that the Hobgoblin was carrying.",
    "icon": {
        "icon_id": 517,
        "color_id": 4
    },
    "jobs": [],
    "sell_price": 185,
    "weight": 0,
    "item_level": 7,
    "crest_slots": 0,
    "quality": 0,
    "can_bazaar": true,
    "craft_recipe": [],
    "gradeup_recipe": [],
    "previous_item_id": 0,
    "next_item_id": 0,
    "shops": [],
    "gather": [
        "Breya Coast: Roaring Tide Cave",
        "Morrow Forest: Invading Demons Cave"
    ],
    "hunt": [
        "Level 30+ Hobgoblin",
        "Level 30+ Hobgoblin Fighter",
        "Level 30+ Hobgoblin Leader",
        "Level 30+ Shadow Goblin Leader",
        "Level 30+ Sling Hobgoblin"
    ],
    "subtype": "other"
}