{
    "type": "material",
    "item_id": 24729,
    "name": "Tree Core Grass",
    "info": "Floral Crafting Material.\nWhile it only grows a few centimeters tall, this\nmysterious plant shines with the same color as the\ncore tree.",
    "icon": {
        "icon_id": 510,
        "color_id": 116
    },
    "jobs": [],
    "sell_price": 900,
    "weight": 0,
    "item_level": 130,
    "crest_slots": 0,
    "quality": 0,
    "can_bazaar": false,
    "craft_recipe": [],
    "gradeup_recipe": [],
    "previous_item_id": 0,
    "next_item_id": 0,
    "shops": [],
    "gather": [],
    "hunt": []
}