{
    "type": "material",
    "item_id": 19294,
    "name": "Cloth of Ambition",
    "info": "Cloth Crafting Material: Cloth filled with\nambition.",
    "icon": {
        "icon_id": 500,
        "color_id": 28
    },
    "jobs": [],
    "sell_price": 300,
    "weight": 0,
    "item_level": 65,
    "crest_slots": 0,
    "quality": 0,
    "can_bazaar": true,
    "craft_recipe": [],
    "gradeup_recipe": [],
    "previous_item_id": 0,
    "next_item_id": 0,
    "shops": [],
    "gather": [],
    "hunt": []
}