{
    "type": "Personal",
    "name": "Deenan Woods Trial: The Stone Fowl in the Ruins",
    "quest_id": 60070001,
    "area_id": "DeenanWoods",
    "guide_type": "AreaTrialOrMission",
    "starting_npc": {
        "id": 4508,
        "name": "Rondejeel0",
        "stage": {
            "name": "Secret Bowmakers Home",
            "id": 105
        }
    },
    "minimum_area_rank": 0,
    "repeatable": false,
    "quest_chain": {
        "previous_quest_id": 0,
        "next_quest_id": 60070002
    },
    "order_conditions": [
        {
            "type": "AreaRank",
            "param01": "DeenanWoods",
            "param02": 4
        }
    ],
    "unlocks": {
        "tutorials": [],
        "contents": [
            "Unlocks Deenan Woods AR5"
        ]
    },
    "description": "To resolve the issue in the Deenan Woods, defeat the Cockatrice that is causing a disturbance at the Divine Blossom Terrace.",
    "steps": [
        "Find the Cockatrice in Divine Blossom Terrace",
        "Defeat the Cockatrice at the ruins",
        "Report to Rondejeel in the Secret Bowmaker's Home"
    ],
    "variants": [
        {
            "level": 43,
            "minimum_item_rank": 0,
            "xp": 5000,
            "gold": 5200,
            "rift": 425,
            "ap": 0,
            "jp": 0,
            "pp": 0,
            "is_bounty": false,
            "rewards": []
        }
    ],
    "tags": []
}