{
    "type": "equipment",
    "item_id": 15397,
    "name": "Royal Guardsman's Sabatons",
    "info": "",
    "icon": {
        "icon_id": 355,
        "color_id": 10
    },
    "jobs": [
        "Fighter",
        "Warrior"
    ],
    "sell_price": 11118,
    "weight": 42,
    "item_level": 60,
    "crest_slots": 0,
    "quality": 3,
    "can_bazaar": false,
    "color_id": 5,
    "equip_slot": "EQUIP_CATEGORY_ARMOR_LEG",
    "level": 77,
    "genders": [
        "Male",
        "Female"
    ],
    "stats": {
        "attack": 2,
        "defense": 321,
        "magic_attack": 2,
        "magic_defense": 257,
        "crest_slot": 0,
        "ele_slot": 24
    },
    "params": [
        {
            "id": 86,
            "name": "ENDURANCE",
            "value": 74
        },
        {
            "id": 69,
            "name": "MAX_STAMINA",
            "value": 735
        }
    ],
    "craft_recipe": [],
    "gradeup_recipe": [
        {
            "item_id": 15975,
            "amount": 5
        },
        {
            "item_id": 15977,
            "amount": 5
        },
        {
            "item_id": 15979,
            "amount": 5
        }
    ],
    "previous_item_id": 15396,
    "next_item_id": 15398
}