{
    "type": "equipment",
    "item_id": 4255,
    "name": "Chimeric Sabatons",
    "info": "",
    "icon": {
        "icon_id": 368,
        "color_id": 10
    },
    "jobs": [
        "Fighter",
        "Warrior"
    ],
    "sell_price": 5620,
    "weight": 72,
    "item_level": 11,
    "crest_slots": 0,
    "quality": 3,
    "can_bazaar": false,
    "color_id": 5,
    "equip_slot": "EQUIP_CATEGORY_ARMOR_LEG",
    "level": 55,
    "genders": [
        "Male",
        "Female"
    ],
    "stats": {
        "attack": 0,
        "defense": 177,
        "magic_attack": 0,
        "magic_defense": 142,
        "crest_slot": 4,
        "ele_slot": 24
    },
    "params": [
        {
            "id": 86,
            "name": "ENDURANCE",
            "value": 49
        },
        {
            "id": 69,
            "name": "MAX_STAMINA",
            "value": 712
        }
    ],
    "craft_recipe": [],
    "gradeup_recipe": [
        {
            "item_id": 7941,
            "amount": 2
        },
        {
            "item_id": 7830,
            "amount": 1
        }
    ],
    "previous_item_id": 3232,
    "next_item_id": 5278
}