{
    "type": "equipment",
    "item_id": 5147,
    "name": "Bronze Bangles",
    "info": "",
    "icon": {
        "icon_id": 20,
        "color_id": 5
    },
    "jobs": [
        "Priest",
        "Sorcerer",
        "ElementArcher"
    ],
    "sell_price": 30,
    "weight": 23,
    "item_level": 1,
    "crest_slots": 0,
    "quality": 4,
    "can_bazaar": false,
    "color_id": 0,
    "equip_slot": "EQUIP_CATEGORY_ARMOR_ARM",
    "level": 3,
    "genders": [
        "Male",
        "Female"
    ],
    "stats": {
        "attack": 0,
        "defense": 24,
        "magic_attack": 0,
        "magic_defense": 20,
        "crest_slot": 4,
        "ele_slot": 32
    },
    "params": [
        {
            "id": 86,
            "name": "ENDURANCE",
            "value": 2
        }
    ],
    "craft_recipe": [],
    "gradeup_recipe": [],
    "previous_item_id": 4124,
    "next_item_id": 0,
    "shops": [],
    "gather": [],
    "hunt": []
}