{
    "type": "equipment",
    "item_id": 12893,
    "name": "Paladin Gloves",
    "info": "",
    "icon": {
        "icon_id": 1311,
        "color_id": 111
    },
    "jobs": [
        "Seeker",
        "Hunter",
        "SpiritLancer"
    ],
    "sell_price": 6339,
    "weight": 34,
    "item_level": 30,
    "crest_slots": 0,
    "quality": 0,
    "can_bazaar": false,
    "color_id": 20,
    "equip_slot": "EQUIP_CATEGORY_ARMOR_ARM",
    "level": 65,
    "genders": [
        "Male",
        "Female"
    ],
    "stats": {
        "attack": 0,
        "defense": 284,
        "magic_attack": 0,
        "magic_defense": 237,
        "crest_slot": 0,
        "ele_slot": 0
    },
    "params": [
        {
            "id": 86,
            "name": "ENDURANCE",
            "value": 14
        },
        {
            "id": 15,
            "name": "RESIST_KNOCKOUT",
            "value": 2
        }
    ],
    "craft_recipe": [
        {
            "item_id": 7943,
            "amount": 2
        },
        {
            "item_id": 7959,
            "amount": 1
        },
        {
            "item_id": 11781,
            "amount": 5
        },
        {
            "item_id": 11782,
            "amount": 3
        },
        {
            "item_id": 11783,
            "amount": 1
        }
    ],
    "gradeup_recipe": [
        {
            "item_id": 11506,
            "amount": 3
        },
        {
            "item_id": 11508,
            "amount": 3
        },
        {
            "item_id": 11504,
            "amount": 3
        }
    ],
    "previous_item_id": 0,
    "next_item_id": 12894
}