{
    "type": "equipment",
    "item_id": 19075,
    "name": "True Road to Hades",
    "info": "",
    "icon": {
        "icon_id": 1687,
        "color_id": 111
    },
    "sell_price": 35805,
    "weight": 80,
    "item_level": 10,
    "quality": 5,
    "color_id": 5,
    "weapon_type": "MAGICK_GAUNTLET",
    "equip_slot": "EQUIP_CATEGORY_WEP_MAIN",
    "level": 1,
    "genders": [
        "Male",
        "Female"
    ],
    "stats": {
        "attack": 2347,
        "magic_attack": 2638,
        "crest_slot": 0,
        "ele_slot": 1
    },
    "params": [
        {
            "id": 84,
            "name": "KIND_TYPE_UNKNOWN",
            "value": 753
        },
        {
            "id": 85,
            "name": "KIND_TYPE_UNKNOWN",
            "value": 5
        }
    ]
}