{
    "type": "equipment",
    "item_id": 3888,
    "name": "Avalon's Beacon",
    "info": "",
    "icon": {
        "icon_id": 1020,
        "color_id": 10
    },
    "jobs": [
        "Priest"
    ],
    "sell_price": 15130,
    "weight": 70,
    "item_level": 11,
    "crest_slots": 1,
    "quality": 3,
    "can_bazaar": false,
    "color_id": 4,
    "weapon_type": "MAGICK_BOW",
    "equip_slot": "EQUIP_CATEGORY_WEP_MAIN",
    "level": 55,
    "genders": [
        "Male",
        "Female"
    ],
    "stats": {
        "attack": 1060,
        "magic_attack": 1131,
        "crest_slot": 4,
        "ele_slot": 25
    },
    "params": [
        {
            "id": 84,
            "name": "BLOW_POWER_SLASHING",
            "value": 168
        }
    ],
    "craft_recipe": [],
    "gradeup_recipe": [
        {
            "item_id": 7748,
            "amount": 2
        },
        {
            "item_id": 8022,
            "amount": 1
        }
    ],
    "previous_item_id": 2865,
    "next_item_id": 4911
}