{
    "type": "equipment",
    "item_id": 5078,
    "name": "Memento Mori",
    "info": "",
    "icon": {
        "icon_id": 975,
        "color_id": 9
    },
    "sell_price": 12010,
    "weight": 80,
    "item_level": 10,
    "quality": 5,
    "color_id": 2,
    "weapon_type": "DAGGER",
    "equip_slot": "EQUIP_CATEGORY_WEP_MAIN",
    "level": 49,
    "genders": [
        "Male",
        "Female"
    ],
    "stats": {
        "attack": 998,
        "magic_attack": 908,
        "crest_slot": 0,
        "ele_slot": 33
    },
    "params": [
        {
            "id": 84,
            "name": "KIND_TYPE_UNKNOWN",
            "value": 200
        },
        {
            "id": 67,
            "name": "KIND_TYPE_UNKNOWN",
            "value": 15
        }
    ]
}