{
    "type": "equipment",
    "item_id": 20294,
    "name": "Rousing Schlucht Shooter",
    "info": "",
    "icon": {
        "icon_id": 1674,
        "color_id": 11
    },
    "jobs": [
        "ElementArcher"
    ],
    "sell_price": 45655,
    "weight": 72,
    "item_level": 115,
    "crest_slots": 1,
    "quality": 0,
    "can_bazaar": false,
    "color_id": 0,
    "weapon_type": "GREATSWORD",
    "equip_slot": "EQUIP_CATEGORY_WEP_MAIN",
    "level": 98,
    "genders": [
        "Male",
        "Female"
    ],
    "stats": {
        "attack": 2968,
        "magic_attack": 3160,
        "crest_slot": 4,
        "ele_slot": 1
    },
    "params": [
        {
            "id": 84,
            "name": "BLOW_POWER_SLASHING",
            "value": 459
        }
    ],
    "craft_recipe": [],
    "gradeup_recipe": [
        {
            "item_id": 17876,
            "amount": 6
        }
    ],
    "previous_item_id": 0,
    "next_item_id": 20295
}