{
    "type": "equipment",
    "item_id": 18720,
    "name": "Rashnu",
    "info": "",
    "icon": {
        "icon_id": 2056,
        "color_id": 111
    },
    "sell_price": 35805,
    "weight": 115,
    "item_level": 10,
    "quality": 5,
    "color_id": 23,
    "weapon_type": "SPIRIT_LANCE",
    "equip_slot": "EQUIP_CATEGORY_WEP_MAIN",
    "level": 85,
    "genders": [
        "Male",
        "Female"
    ],
    "stats": {
        "attack": 2502,
        "magic_attack": 2402,
        "crest_slot": 0,
        "ele_slot": 1
    },
    "params": [
        {
            "id": 84,
            "name": "KIND_TYPE_UNKNOWN",
            "value": 481
        },
        {
            "id": 85,
            "name": "KIND_TYPE_UNKNOWN",
            "value": 10
        },
        {
            "id": 67,
            "name": "KIND_TYPE_UNKNOWN",
            "value": 15
        }
    ]
}