{
    "type": "equipment",
    "item_id": 11621,
    "name": "True Religious Beyond",
    "info": "",
    "icon": {
        "icon_id": 999,
        "color_id": 25
    },
    "jobs": [
        "ElementArcher"
    ],
    "sell_price": 16825,
    "weight": 60,
    "item_level": 12,
    "crest_slots": 1,
    "quality": 4,
    "can_bazaar": false,
    "color_id": 20,
    "weapon_type": "GREATSWORD",
    "equip_slot": "EQUIP_CATEGORY_WEP_MAIN",
    "level": 40,
    "genders": [
        "Male",
        "Female"
    ],
    "stats": {
        "attack": 1220,
        "magic_attack": 1376,
        "crest_slot": 0,
        "ele_slot": 33
    },
    "params": [
        {
            "id": 84,
            "name": "BLOW_POWER_SLASHING",
            "value": 214
        },
        {
            "id": 85,
            "name": "BLOW_POWER_BBLUNT",
            "value": 10
        },
        {
            "id": 94,
            "name": "WINGED_SLAYER",
            "value": 63
        }
    ],
    "craft_recipe": [],
    "gradeup_recipe": [],
    "previous_item_id": 11620,
    "next_item_id": 0,
    "shops": [],
    "gather": [],
    "hunt": []
}