{
    "type": "equipment",
    "item_id": 14595,
    "name": "Tannh\u00e4user",
    "info": "",
    "icon": {
        "icon_id": 996,
        "color_id": 10
    },
    "jobs": [
        "ElementArcher"
    ],
    "sell_price": 28130,
    "weight": 60,
    "item_level": 50,
    "crest_slots": 1,
    "quality": 3,
    "can_bazaar": false,
    "color_id": 1,
    "weapon_type": "GREATSWORD",
    "equip_slot": "EQUIP_CATEGORY_WEP_MAIN",
    "level": 75,
    "genders": [
        "Male",
        "Female"
    ],
    "stats": {
        "attack": 1787,
        "magic_attack": 1956,
        "crest_slot": 0,
        "ele_slot": 25
    },
    "params": [
        {
            "id": 84,
            "name": "BLOW_POWER_SLASHING",
            "value": 297
        },
        {
            "id": 55,
            "name": "INFLICT_FROZEN_SOLID",
            "value": 18
        }
    ],
    "craft_recipe": [],
    "gradeup_recipe": [
        {
            "item_id": 15929,
            "amount": 3
        },
        {
            "item_id": 15931,
            "amount": 3
        }
    ],
    "previous_item_id": 14594,
    "next_item_id": 14596
}