{
    "type": "equipment",
    "item_id": 19193,
    "name": "Crimson Wand",
    "info": "",
    "icon": {
        "icon_id": 1389,
        "color_id": 111
    },
    "jobs": [
        "Sorcerer"
    ],
    "sell_price": 32005,
    "weight": 80,
    "item_level": 75,
    "crest_slots": 1,
    "quality": 4,
    "can_bazaar": false,
    "color_id": 4,
    "weapon_type": "MAGICK_GAUNTLET",
    "equip_slot": "EQUIP_CATEGORY_WEP_MAIN",
    "level": 80,
    "genders": [
        "Male",
        "Female"
    ],
    "stats": {
        "attack": 2149,
        "magic_attack": 2432,
        "crest_slot": 4,
        "ele_slot": 33
    },
    "params": [
        {
            "id": 84,
            "name": "BLOW_POWER_SLASHING",
            "value": 684
        },
        {
            "id": 85,
            "name": "BLOW_POWER_BBLUNT",
            "value": 10
        },
        {
            "id": 102,
            "name": "DRAGON_SLAYER",
            "value": 36
        }
    ],
    "craft_recipe": [],
    "gradeup_recipe": [],
    "previous_item_id": 19192,
    "next_item_id": 0,
    "shops": [],
    "gather": [],
    "hunt": []
}