{
    "type": "equipment",
    "item_id": 526,
    "name": "Serenity Helm",
    "info": "",
    "icon": {
        "icon_id": 234,
        "color_id": 7
    },
    "jobs": [
        "Fighter",
        "Warrior"
    ],
    "sell_price": 1440,
    "weight": 36,
    "item_level": 6,
    "crest_slots": 0,
    "quality": 0,
    "can_bazaar": false,
    "color_id": 1,
    "equip_slot": "EQUIP_CATEGORY_ARMOR_HELM",
    "level": 30,
    "genders": [
        "Male",
        "Female"
    ],
    "stats": {
        "attack": 0,
        "defense": 73,
        "magic_attack": 0,
        "magic_defense": 117,
        "crest_slot": 0,
        "ele_slot": 0
    },
    "params": [],
    "craft_recipe": [
        {
            "item_id": 7879,
            "amount": 1
        },
        {
            "item_id": 7779,
            "amount": 1
        },
        {
            "item_id": 7804,
            "amount": 2
        }
    ],
    "gradeup_recipe": [
        {
            "item_id": 7861,
            "amount": 1
        }
    ],
    "previous_item_id": 0,
    "next_item_id": 2138
}