{
    "type": "World",
    "name": "Phantom Thieves: Omen of Madness",
    "quest_id": 20005013,
    "area_id": "HidellPlains",
    "guide_type": "QuestUsefulForAdventure",
    "starting_npc": null,
    "minimum_area_rank": 1,
    "repeatable": true,
    "quest_chain": {
        "previous_quest_id": 0,
        "next_quest_id": 0
    },
    "order_conditions": [],
    "unlocks": {
        "tutorials": [],
        "contents": []
    },
    "description": "Listen to the requester's wishes and lend your aid",
    "steps": [
        "Go to the designated location and investigate.",
        "Eliminate the interfering enemies",
        "Report to the requester"
    ],
    "variants": [
        {
            "level": 10,
            "minimum_item_rank": 0,
            "xp": 555,
            "gold": 555,
            "rift": 55,
            "ap": 80,
            "jp": 0,
            "pp": 0,
            "is_bounty": false,
            "rewards": [
                {
                    "type": "Select1",
                    "pools": [
                        [
                            {
                                "name": "Thief Card",
                                "item_id": 13810,
                                "amount": 20
                            },
                            {
                                "name": "Enhanced Lockpick",
                                "item_id": 9403,
                                "amount": 2
                            },
                            {
                                "name": "Small Thief's Key",
                                "item_id": 9429,
                                "amount": 2
                            },
                            {
                                "name": "Random Rewards",
                                "amount": 1
                            }
                        ]
                    ]
                }
            ]
        }
    ],
    "tags": []
}