{
    "type": "equipment",
    "item_id": 13116,
    "name": "Traditional Underwear",
    "info": "",
    "icon": {
        "icon_id": 805,
        "color_id": 10
    },
    "sell_price": 1441,
    "weight": 5,
    "item_level": 15,
    "quality": 7,
    "color_id": 0,
    "equip_slot": "EQUIP_CATEGORY_WEAR_LEG",
    "level": 62,
    "genders": [
        "Male",
        "Female"
    ],
    "stats": {
        "attack": 0,
        "defense": 82,
        "magic_attack": 0,
        "magic_defense": 82,
        "crest_slot": 4,
        "ele_slot": 24
    },
    "params": [
        {
            "id": 86,
            "name": "KIND_TYPE_UNKNOWN",
            "value": 34
        },
        {
            "id": 69,
            "name": "KIND_TYPE_MAX_ST_UP",
            "value": 254
        }
    ]
}