{
    "type": "equipment",
    "item_id": 9057,
    "name": "Hellfang",
    "info": "",
    "icon": {
        "icon_id": 851,
        "color_id": 8
    },
    "jobs": [
        "Fighter"
    ],
    "sell_price": 2890,
    "weight": 20,
    "item_level": 8,
    "crest_slots": 0,
    "quality": 3,
    "can_bazaar": false,
    "color_id": 3,
    "weapon_type": "SHIELD",
    "equip_slot": "EQUIP_CATEGORY_WEP_SUB",
    "level": 40,
    "genders": [
        "Male",
        "Female"
    ],
    "stats": {
        "attack": 0,
        "magic_attack": 0,
        "crest_slot": 0,
        "ele_slot": 24
    },
    "params": [
        {
            "id": 87,
            "name": "GUARD_POWER",
            "value": 256
        },
        {
            "id": 30,
            "name": "BLOCKING_STAMINA_REDUCTION",
            "value": 15
        }
    ],
    "craft_recipe": [],
    "gradeup_recipe": [
        {
            "item_id": 7884,
            "amount": 2
        },
        {
            "item_id": 7815,
            "amount": 1
        },
        {
            "item_id": 7801,
            "amount": 1
        }
    ],
    "previous_item_id": 9056,
    "next_item_id": 9058
}