{
    "type": "equipment",
    "item_id": 20137,
    "name": "Brave Shield",
    "info": "",
    "icon": {
        "icon_id": 2301,
        "color_id": 11
    },
    "jobs": [
        "Fighter"
    ],
    "sell_price": 9388,
    "weight": 44,
    "crest_slots": 0,
    "quality": 2,
    "can_bazaar": false,
    "item_level": 6,
    "color_id": 23,
    "weapon_type": "SHIELD",
    "equip_slot": "EQUIP_CATEGORY_WEP_SUB",
    "level": 100,
    "genders": [
        "Male",
        "Female"
    ],
    "stats": {
        "attack": 0,
        "magic_attack": 0,
        "crest_slot": 0,
        "ele_slot": 16
    },
    "params": [
        {
            "id": 87,
            "name": "GUARD_POWER",
            "value": 502
        },
        {
            "id": 30,
            "name": "BLOCKING_STAMINA_REDUCTION",
            "value": 12
        }
    ]
}